odoo10_addon_website_sale_affiliate-10.0.1.0.1-py2.7-nspkg.pth
odoo/addons/website_sale_affiliate/README.rst
odoo/addons/website_sale_affiliate/__init__.py
odoo/addons/website_sale_affiliate/__manifest__.py
odoo/addons/website_sale_affiliate/controllers/__init__.py
odoo/addons/website_sale_affiliate/controllers/main.py
odoo/addons/website_sale_affiliate/data/sale_affiliate_data.xml
odoo/addons/website_sale_affiliate/demo/sale_affiliate_demo.xml
odoo/addons/website_sale_affiliate/i18n/am.po
odoo/addons/website_sale_affiliate/i18n/ar.po
odoo/addons/website_sale_affiliate/i18n/bg.po
odoo/addons/website_sale_affiliate/i18n/bs.po
odoo/addons/website_sale_affiliate/i18n/ca.po
odoo/addons/website_sale_affiliate/i18n/cs.po
odoo/addons/website_sale_affiliate/i18n/da.po
odoo/addons/website_sale_affiliate/i18n/de.po
odoo/addons/website_sale_affiliate/i18n/el_GR.po
odoo/addons/website_sale_affiliate/i18n/en_GB.po
odoo/addons/website_sale_affiliate/i18n/es.po
odoo/addons/website_sale_affiliate/i18n/es_AR.po
odoo/addons/website_sale_affiliate/i18n/es_CL.po
odoo/addons/website_sale_affiliate/i18n/es_CO.po
odoo/addons/website_sale_affiliate/i18n/es_CR.po
odoo/addons/website_sale_affiliate/i18n/es_DO.po
odoo/addons/website_sale_affiliate/i18n/es_EC.po
odoo/addons/website_sale_affiliate/i18n/es_ES.po
odoo/addons/website_sale_affiliate/i18n/es_MX.po
odoo/addons/website_sale_affiliate/i18n/es_PE.po
odoo/addons/website_sale_affiliate/i18n/es_PY.po
odoo/addons/website_sale_affiliate/i18n/es_VE.po
odoo/addons/website_sale_affiliate/i18n/et.po
odoo/addons/website_sale_affiliate/i18n/eu.po
odoo/addons/website_sale_affiliate/i18n/fa.po
odoo/addons/website_sale_affiliate/i18n/fi.po
odoo/addons/website_sale_affiliate/i18n/fr.po
odoo/addons/website_sale_affiliate/i18n/fr_CA.po
odoo/addons/website_sale_affiliate/i18n/fr_CH.po
odoo/addons/website_sale_affiliate/i18n/gl.po
odoo/addons/website_sale_affiliate/i18n/gl_ES.po
odoo10_addon_website_sale_affiliate-10.0.1.0.1.dist-info/METADATA
odoo10_addon_website_sale_affiliate-10.0.1.0.1.dist-info/RECORD
odoo10_addon_website_sale_affiliate-10.0.1.0.1.dist-info/WHEEL
odoo10_addon_website_sale_affiliate-10.0.1.0.1.dist-info/namespace_packages.txt
odoo10_addon_website_sale_affiliate-10.0.1.0.1.dist-info/top_level.txt
